[
  {
    "title": "\"Эмч, сувилагчдын цалинг нэг шатлалтай болгоход 150 тэрбум төгрөг шаардлагатай\"",
    "link": "https://news.mn/r/2861111/",
    "scraped_at": "2026-04-16 01:08:35 +0800"
  },
  {
    "title": "Байр суурь: Парламентын ардчиллаа хамгаалах асуудлаар гишүүд юу хэлэв!",
    "link": "https://news.mn/r/2861144/",
    "scraped_at": "2026-04-16 01:08:35 +0800"
  },
  {
    "title": "\"ОХУ Хятадын эрчим хүчний хомсдолыг нөхөх боломжтой\"",
    "link": "https://news.mn/r/2861128/",
    "scraped_at": "2026-04-16 01:08:35 +0800"
  },
  {
    "title": "Монгол хэл, бичгийн шалгалтын сэдвүүдийг нээлттэй зарладаг болно",
    "link": "https://news.mn/r/2861152/",
    "scraped_at": "2026-04-16 01:08:35 +0800"
  },
  {
    "title": "250 цагаач тээвэрлэж явсан завь хөмөрчээ",
    "link": "https://news.mn/r/2861148/",
    "scraped_at": "2026-04-16 01:08:35 +0800"
  },
  {
    "title": "Сэлэнгэ Бодонс багт эргэн ирэх хүч, боломж үлдсэн үү?",
    "link": "https://news.mn/r/2861056/",
    "scraped_at": "2026-04-16 01:08:35 +0800"
  },
  {
    "title": "\"Маршлын гүүр орчмын уснаас гэдэсний савханцар нян илэрсэн\"",
    "link": "https://news.mn/r/2861109/",
    "scraped_at": "2026-04-16 01:08:35 +0800"
  },
  {
    "title": "Дэлхийн газрын тосны нийлүүлэлт огцом буурсан байна",
    "link": "https://news.mn/r/2861147/",
    "scraped_at": "2026-04-16 01:08:35 +0800"
  },
  {
    "title": "ЦЕГ-ын дарга Ж.Болдыг Ц.Ням-Очироор солих уу?",
    "link": "https://news.mn/r/2861081/",
    "scraped_at": "2026-04-16 01:08:35 +0800"
  },
  {
    "title": "Инфляцын түвшин 7.4 хувиар өсөв",
    "link": "https://news.mn/r/2861057/",
    "scraped_at": "2026-04-16 01:08:35 +0800"
  },
  {
    "title": "Израиль болон Ливаны хооронд дипломат уулзалт боллоо",
    "link": "https://news.mn/r/2861046/",
    "scraped_at": "2026-04-16 01:08:35 +0800"
  },
  {
    "title": "Ардчилсан намын ЕНБД-ын үүрэг гүйцэтгэгчээр С.Баярцогтыг томилов",
    "link": "https://news.mn/r/2861117/",
    "scraped_at": "2026-04-16 01:08:35 +0800"
  },
  {
    "title": "ЭМЯ-ны Төрийн нарийн бичгийн дарга Д.Очирбатыг чөлөөлжээ",
    "link": "https://news.mn/r/2861185/",
    "scraped_at": "2026-04-16 01:08:35 +0800"
  },
  {
    "title": "Хятадын пуужингийн мэргэжилтэн Фэн Юйфан нас баржээ",
    "link": "https://news.mn/r/2861155/",
    "scraped_at": "2026-04-16 01:08:35 +0800"
  },
  {
    "title": "ЗГХЭГ-ын тэргүүн дэд даргаар Б.Батцэцэгийг томиллоо",
    "link": "https://news.mn/r/2861129/",
    "scraped_at": "2026-04-16 01:08:35 +0800"
  },
  {
    "title": "Япон улс 10 тэрбум долларын багц танилцуулна",
    "link": "https://news.mn/r/2861115/",
    "scraped_at": "2026-04-16 01:08:35 +0800"
  },
  {
    "title": "Б.Батцэцэг дипломат ёсыг ноцтой зөрчиж улсынхаа нэрийг шавартай хутгав",
    "link": "https://news.mn/r/2861108/",
    "scraped_at": "2026-04-16 01:08:35 +0800"
  },
  {
    "title": "Амралт, зуслангийн нэр барин 80 сая төгрөг залилжээ",
    "link": "https://news.mn/r/2861075/",
    "scraped_at": "2026-04-16 01:08:35 +0800"
  },
  {
    "title": "Таны хэрэглээнд ойр ₮ кредит карт",
    "link": "https://news.mn/r/2861104/",
    "scraped_at": "2026-04-16 01:08:35 +0800"
  },
  {
    "title": "Хөшөө үнссэн эр 6 сарын ял авлаа",
    "link": "https://news.mn/r/2861041/",
    "scraped_at": "2026-04-16 01:08:35 +0800"
  },
  {
    "title": "Сурагчдад замын хөдөлгөөний дүрмийн сургалт оров",
    "link": "https://news.mn/r/2861052/",
    "scraped_at": "2026-04-16 01:08:35 +0800"
  },
  {
    "title": "\"BYD\"-ийн үйлдвэрийн галын шалтгааныг тогтоогоогүй",
    "link": "https://news.mn/r/2861017/",
    "scraped_at": "2026-04-16 01:08:35 +0800"
  },
  {
    "title": "З.Энхболд нарын шүүх хурал 3 дахь өдрөө үргэлжилж байна",
    "link": "https://news.mn/r/2860739/",
    "scraped_at": "2026-04-16 01:08:35 +0800"
  },
  {
    "title": "1.2 сая доллараар үнэлэгдэх бүтээлийг 118 доллараар хожжээ",
    "link": "https://news.mn/r/2861015/",
    "scraped_at": "2026-04-16 01:08:35 +0800"
  },
  {
    "title": "Улаанбаатар–Өндөрхаан чиглэлийн замыг түр хугацаанд хаана",
    "link": "https://news.mn/r/2861026/",
    "scraped_at": "2026-04-16 01:08:35 +0800"
  },
  {
    "title": "Сурвалжлага: Далан давхрын цэцэрлэгт хүрээлэн хандивгүйгээс гацжээ",
    "link": "https://news.mn/r/2860985/",
    "scraped_at": "2026-04-16 01:08:35 +0800"
  },
  {
    "title": "“Онцгойрч үлдэх олимп” ном хэвлэгдлээ",
    "link": "https://news.mn/r/2861019/",
    "scraped_at": "2026-04-16 01:08:35 +0800"
  },
  {
    "title": "ОУВС дэлхийн эдийн засгийн төлөвийг 3 хувилбараар танилцуулжээ",
    "link": "https://news.mn/r/2861014/",
    "scraped_at": "2026-04-16 01:08:35 +0800"
  },
  {
    "title": " Авлигын хэргээр 13 жилийн ял авсан Л.Бямбасүрэн гэж хэн бэ!",
    "link": "https://news.mn/r/2861008/",
    "scraped_at": "2026-04-16 01:08:35 +0800"
  },
  {
    "title": "Хятадын Гадаад хэргийн дэд сайд огцорчээ",
    "link": "https://news.mn/r/2861004/",
    "scraped_at": "2026-04-16 01:08:35 +0800"
  },
  {
    "title": "ЗГ: Эрүүл мэндийн салбарынхны цалинг хэлэлцэж байна",
    "link": "https://news.mn/r/2861002/",
    "scraped_at": "2026-04-16 01:08:35 +0800"
  },
  {
    "title": "Ньюс хөтөч: Түүхийн багш нарын анхдугаар зөвлөгөөн болно",
    "link": "https://news.mn/r/2860998/",
    "scraped_at": "2026-04-16 01:08:35 +0800"
  },
  {
    "title": "\"Засгийн газрын 8 сайд БЗС-гийн зээлээ, хүүгээ төлөөгүй байна\"",
    "link": "https://news.mn/r/2860790/",
    "scraped_at": "2026-04-16 01:08:35 +0800"
  },
  {
    "title": "\"Эрэгтэй хүүхдүүд монгол хэл, бичгийн босго давж чадахгүй байна\"",
    "link": "https://news.mn/r/2860857/",
    "scraped_at": "2026-04-16 01:08:35 +0800"
  },
  {
    "title": "Фото: \"Coachella\" бол загвар, урлагийн хослол",
    "link": "https://news.mn/r/2860858/",
    "scraped_at": "2026-04-16 01:08:35 +0800"
  },
  {
    "title": "Ерөнхий сайд аа, ТӨБЗГ-ын дарга Б.Цэнгэлдээ хариуцлага тооцно уу!",
    "link": "https://news.mn/r/2860787/",
    "scraped_at": "2026-04-16 01:08:35 +0800"
  },
  {
    "title": "АУДИТ: Г.Ёндоны будлиантай тендер ил болов",
    "link": "https://news.mn/r/2860965/",
    "scraped_at": "2026-04-16 01:08:35 +0800"
  },
  {
    "title": "VS: Нүүрсээ 50 хувь хямд зарсан, зараагүй",
    "link": "https://news.mn/r/2860813/",
    "scraped_at": "2026-04-16 01:08:35 +0800"
  },
  {
    "title": "Монгол төрийн өр огцом өссөн ч өгөөж нь хангалтгүй байна",
    "link": "https://news.mn/r/2860756/",
    "scraped_at": "2026-04-16 01:08:35 +0800"
  },
  {
    "title": "Ливанчуудын хүсээгүй дайн",
    "link": "https://news.mn/r/2860777/",
    "scraped_at": "2026-04-16 01:08:35 +0800"
  },
  {
    "title": "1 ч шүдгүй болсон эр сэтгэлээр унасандаа амиа хорложээ",
    "link": "https://news.mn/r/2860752/",
    "scraped_at": "2026-04-16 01:08:35 +0800"
  },
  {
    "title": "\"Coachella-2026\" хөгжмийн урсгалыг тодорхойлж байна",
    "link": "https://news.mn/r/2860454/",
    "scraped_at": "2026-04-16 01:08:35 +0800"
  },
  {
    "title": "Меланиа: Намайг Эпштейнтэй холбодог мэдэгдлүүдэд цэг тавина",
    "link": "https://news.mn/r/2859999/",
    "scraped_at": "2026-04-16 01:08:35 +0800"
  },
  {
    "title": "Тулааны талбар дээрх \"үзэсгэлэн гоо\" жанжинтай кинонуудыг эсэргүүцэж байна",
    "link": "https://news.mn/r/2859139/",
    "scraped_at": "2026-04-16 01:08:35 +0800"
  },
  {
    "title": "Фото : Алхах зам уу, саад бэрхшээл үү?",
    "link": "https://news.mn/r/2858466/",
    "scraped_at": "2026-04-16 01:08:35 +0800"
  },
  {
    "title": "Фото: Ерөнхий сайд Г.Занданшатарыг өөрийнх нь хүсэлтээр чөлөөллөө",
    "link": "https://news.mn/r/2857452/",
    "scraped_at": "2026-04-16 01:08:35 +0800"
  },
  {
    "title": "Фото: 2026 оны УИХ-ын хаврын чуулганыг нээлээ",
    "link": "https://news.mn/r/2854824/",
    "scraped_at": "2026-04-16 01:08:35 +0800"
  },
  {
    "title": "\"Дэлгэцийн донтолт сэтгэл гутралд өртөх эрсдэлийг 80 хувь нэмдэг\"",
    "link": "https://news.mn/r/2779436/",
    "scraped_at": "2026-04-16 01:08:35 +0800"
  },
  {
    "title": "\"Монгол эрдэмтдийн бүтээлийг эдийн засгийн эргэлтэд оруулахыг дэмжинэ\"",
    "link": "https://news.mn/r/2694133/",
    "scraped_at": "2026-04-16 01:08:35 +0800"
  },
  {
    "title": "\"120 хуулийн өөрчлөлт цахим шилжилтийн том реформ болно\"",
    "link": "https://news.mn/r/2692133/",
    "scraped_at": "2026-04-16 01:08:35 +0800"
  },
  {
    "title": "ИЦББХ: Төр байгаа мэдээллээ цаасаар нэхдэг байдлыг хална",
    "link": "https://news.mn/r/2691969/",
    "scraped_at": "2026-04-16 01:08:35 +0800"
  },
  {
    "title": "Г.Түвдэндоржийн \"АЖЛЫН ЦАГ\"",
    "link": "https://news.mn/r/2716454/",
    "scraped_at": "2026-04-16 01:08:35 +0800"
  },
  {
    "title": "\"Хотын олон асуудлыг шийдвэрлэж чадах баг бүрдүүлж, НИТХ-ын сонгуульд нэр дэвшүүллээ\"",
    "link": "https://news.mn/r/2748217/",
    "scraped_at": "2026-04-16 01:08:35 +0800"
  },
  {
    "title": "Нэр дэвшигчийг УИХ-ын гишүүнээр сонгогдсонд тооцов",
    "link": "https://news.mn/r/2735467/",
    "scraped_at": "2026-04-16 01:08:35 +0800"
  },
  {
    "title": "АН: Хэсгийн ахлагч нар \"Заавал МАН-ыг дэмжинэ шүү\" гэж байна",
    "link": "https://news.mn/r/2735073/",
    "scraped_at": "2026-04-16 01:08:35 +0800"
  },
  {
    "title": "“Мосфильм” кино студийг Путин магтжээ",
    "link": "https://news.mn/r/2763891/",
    "scraped_at": "2026-04-16 01:08:35 +0800"
  },
  {
    "title": "\"Зөвлөл дэвтрийн нүүрэнд багтахааргүй их ажил хийсэн\"",
    "link": "https://news.mn/r/2763782/",
    "scraped_at": "2026-04-16 01:08:35 +0800"
  },
  {
    "title": "“Оюутолгой” ХХК-ийн ТУЗ-ийн гишүүнээр Э.Мэндтүвшинг томилжээ",
    "link": "https://news.mn/r/2763749/",
    "scraped_at": "2026-04-16 01:08:35 +0800"
  },
  {
    "title": "Сурвалжлага: \"Нэгнээ пингвин алхалтаар явахгүй яасан юм гэдэг\"",
    "link": "https://news.mn/r/2763345/",
    "scraped_at": "2026-04-16 01:08:35 +0800"
  },
  {
    "title": "Сурвалжлага: Байрны хаалга, шал, цахилгааны утсыг нь тоножээ",
    "link": "https://news.mn/r/2763095/",
    "scraped_at": "2026-04-16 01:08:35 +0800"
  },
  {
    "title": "Сурвалжлага: Таны зургийг хиймэл оюун ухаанаар өөрчилж, хэвлэнэ",
    "link": "https://news.mn/r/2762890/",
    "scraped_at": "2026-04-16 01:08:35 +0800"
  },
  {
    "title": "\"Хамас бүлгэм энгийн иргэдээр нуувч хийж байна\"",
    "link": "https://news.mn/r/2738099/",
    "scraped_at": "2026-04-16 01:08:35 +0800"
  },
  {
    "title": "\"Хятад НҮБ-ын Тогтвортой хөгжил хөтөлбөрийн ядуурлыг бууруулах зорилтыг 10 жилийн өмнө биелүүллээ\"",
    "link": "https://news.mn/r/2499381/",
    "scraped_at": "2026-04-16 01:08:35 +0800"
  },
  {
    "title": "\"Солонгос, Монгол хоёр өгөөмөр, тусч зангаараа дэндүү ижилхэн\"",
    "link": "https://news.mn/r/2335441/",
    "scraped_at": "2026-04-16 01:08:35 +0800"
  },
  {
    "title": "Илжигний чихэнд алт хийсэн ч",
    "link": "http://baabar.mn/article/iljignii-chikhend-alt-khiisen-ch?year=2024&month=11&day=14",
    "scraped_at": "2026-04-16 01:08:35 +0800"
  },
  {
    "title": "Л.Оюун-Эрдэнэ “тооноор оруулсан гийчид”-дээ ноцуулж, галзуу шийдвэрийнхээ горыг амсаж байна",
    "link": "http://baabar.mn/article/l-oyuun-erdene-toonoor-oruulsan-giichid-dee-notsuulj-galzuu-shiidweriinkhee-goriig-amsaj-baina?year=2024&month=11&day=14",
    "scraped_at": "2026-04-16 01:08:35 +0800"
  },
  {
    "title": "Улсаасаа баян хүн байна... гэв үү?",
    "link": "http://baabar.mn/article/ulsaasaa-bayan-khun-baina-gew-uu?year=2024&month=11&day=13",
    "scraped_at": "2026-04-16 01:08:35 +0800"
  },
  {
    "title": "Улаанбаатарт 6 хэм дулаан, үүл багасна",
    "link": "https://news.mn/r/2860796/",
    "scraped_at": "2026-04-16 01:08:35 +0800"
  }
]